mkdocs_nav_includer_plugin/__init__.py
mkdocs_nav_includer_plugin/includer.py
mkdocs_nav_includer_plugin/plugin.py
mkdocs_nav_includer_plugin-0.1.0.dist-info/LICENSE
mkdocs_nav_includer_plugin-0.1.0.dist-info/METADATA
mkdocs_nav_includer_plugin-0.1.0.dist-info/WHEEL
mkdocs_nav_includer_plugin-0.1.0.dist-info/entry_points.txt
mkdocs_nav_includer_plugin-0.1.0.dist-info/top_level.txt
mkdocs_nav_includer_plugin-0.1.0.dist-info/RECORD
