Metadata-Version: 2.1
Name: mkdocs-nav-includer-plugin
Version: 0.1.0
Summary: Plugin for improving nav in Mkdocs.
Home-page: https://github.com/TEDmn/mkdocs-nav-includer-plugin
Author: Teddy "TEDmk" Turquet
Author-email: teddy.turquet@protonmail.com
License: MIT
Keywords: mkdocs nav includer
Platform: UNKNOWN
Classifier: Development Status :: 4 - Beta
Classifier: Intended Audience :: Developers
Classifier: Intended Audience :: Information Technology
Classifier: Programming Language :: Python
Classifier: Programming Language :: Python :: 3 :: Only
Classifier: Programming Language :: Python :: 3.5
Classifier: Programming Language :: Python :: 3.6
Classifier: Programming Language :: Python :: 3.7
Requires-Python: >=3
Requires-Dist: mkdocs (>=1.0.4)
